normi/__init__.py
normi/__main__.py
normi/_estimators.py
normi/_typing.py
normi/_utils.py
normi-0.2.0.dist-info/LICENSE
normi-0.2.0.dist-info/METADATA
normi-0.2.0.dist-info/WHEEL
normi-0.2.0.dist-info/entry_points.txt
normi-0.2.0.dist-info/top_level.txt
normi-0.2.0.dist-info/RECORD
