Metadata-Version: 2.1
Name: normi
Version: 0.2.0
Summary: Estimator for Normalized Mutual Information
Home-page: https://github.com/moldyn/NorMI
Author: braniii
License: MIT License
Project-URL: Documentation, https://moldyn.github.io/NorMI
Project-URL: Source Code, https://github.com/moldyn/NorMI
Project-URL: Changelog, https://moldyn.github.io/NorMI/changelog
Project-URL: Bug Tracker, https://github.com/moldyn/NorMI/issues
Keywords: normalized mutual information,mutual information,Kraskov Estimator,KSG Estimator
Classifier: License :: OSI Approved :: MIT License
Classifier: Intended Audience :: Science/Research
Classifier: Natural Language :: English
Classifier: Programming Language :: Python :: 3
Classifier: Programming Language :: Python :: 3.8
Classifier: Programming Language :: Python :: 3.9
Classifier: Programming Language :: Python :: 3.10
Classifier: Programming Language :: Python :: 3.11
Classifier: Programming Language :: Python :: 3.12
Classifier: Topic :: Scientific/Engineering :: Bio-Informatics
Classifier: Topic :: Scientific/Engineering :: Information Analysis
Classifier: Topic :: Scientific/Engineering :: Physics
Classifier: Topic :: Software Development :: Libraries :: Python Modules
Requires-Python: >=3.8
License-File: LICENSE
Requires-Dist: numpy >=1.21.0
Requires-Dist: scipy
Requires-Dist: click >=8.0.0
Requires-Dist: beartype >=0.10.4
Requires-Dist: tqdm
Requires-Dist: scikit-learn >=1.0.0
Requires-Dist: typing-extensions >=3.9.0 ; python_version < "3.9"
Provides-Extra: all
Requires-Dist: pytest-rerunfailures ; extra == 'all'
Requires-Dist: wemake-python-styleguide ; extra == 'all'
Requires-Dist: pytest ; extra == 'all'
Requires-Dist: mkdocs-section-index ; extra == 'all'
Requires-Dist: mkdocs-click ; extra == 'all'
Requires-Dist: mkdocs-literate-nav ; extra == 'all'
Requires-Dist: flake8 ; extra == 'all'
Requires-Dist: mkdocs-gen-files ; extra == 'all'
Requires-Dist: mkdocs-material ; extra == 'all'
Requires-Dist: mkdocstrings-python ; extra == 'all'
Requires-Dist: mkdocstrings ; extra == 'all'
Requires-Dist: pytest-cov ; extra == 'all'
Provides-Extra: coding
Requires-Dist: wemake-python-styleguide ; extra == 'coding'
Provides-Extra: docs
Requires-Dist: mkdocs-section-index ; extra == 'docs'
Requires-Dist: mkdocs-click ; extra == 'docs'
Requires-Dist: mkdocs-literate-nav ; extra == 'docs'
Requires-Dist: mkdocs-gen-files ; extra == 'docs'
Requires-Dist: mkdocstrings-python ; extra == 'docs'
Requires-Dist: mkdocstrings ; extra == 'docs'
Requires-Dist: mkdocs-material ; extra == 'docs'
Provides-Extra: testing
Requires-Dist: pytest-rerunfailures ; extra == 'testing'
Requires-Dist: pytest ; extra == 'testing'
Requires-Dist: flake8 ; extra == 'testing'
Requires-Dist: pytest-cov ; extra == 'testing'
